sinetra/__init__.py
sinetra/emission.py
sinetra/main.py
sinetra/mask.py
sinetra/motion.py
sinetra/optical_flow.py
sinetra/particle.py
sinetra/py.typed
sinetra/random.py
sinetra/simulator.py
sinetra/springs.py
sinetra-0.1.5.dist-info/licenses/LICENSE
sinetra-0.1.5.dist-info/METADATA
sinetra-0.1.5.dist-info/WHEEL
sinetra-0.1.5.dist-info/top_level.txt
sinetra-0.1.5.dist-info/RECORD
