Metadata-Version: 2.4
Name: sinetra
Version: 0.1.5
Summary: Generate synthetic data for biological particle tracking
Home-page: https://github.com/raphaelreme/sinetra
Author: Raphael Reme
Author-email: raphaelreme-dev@protonmail.com
License: MIT
Keywords: Tracking,simulator,biology,statistics,optimization
Classifier: Development Status :: 4 - Beta
Classifier: License :: OSI Approved :: MIT License
Classifier: Natural Language :: English
Classifier: Operating System :: OS Independent
Classifier: Programming Language :: Python :: 3.9
Classifier: Programming Language :: Python :: 3.10
Classifier: Programming Language :: Python :: 3.11
Classifier: Programming Language :: Python :: 3.12
Classifier: Programming Language :: Python :: 3.13
Requires-Python: >=3.9
License-File: LICENSE
Requires-Dist: byotrack
Requires-Dist: dacite
Requires-Dist: pyyaml
Dynamic: license-file
